lestra/__init__.py
lestra/_parser.py
lestra/ext.py
lestra/io.py
lestra-0.0.3.dist-info/METADATA
lestra-0.0.3.dist-info/WHEEL
lestra-0.0.3.dist-info/RECORD
