Metadata-Version: 2.4
Name: lestra
Version: 0.0.3
Author: lestra
Requires-Python: >=3.8
Requires-Dist: typing-extensions
